README.md
setup.py
deltatuner/__init__.py
deltatuner/deltatuner.py
deltatuner/deltatuner_args.py
deltatuner/deltatuner_model.py
deltatuner/mapping.py
deltatuner/version
deltatuner/conf/best_structure/gpt2-best_structure.jsonl
deltatuner/conf/best_structure/EleutherAI/gpt-j-6b-best_structure.jsonl
deltatuner/conf/best_structure/bigscience/bloom-560m-best_structure.jsonl
deltatuner/conf/best_structure/facebook/opt-125m-best_structure.jsonl
deltatuner/conf/best_structure/meta-llama/Llama-2-7b-hf-best_structure.jsonl
deltatuner/conf/best_structure/mosaicml/mpt-7b-best_structure.jsonl
deltatuner/scores/__init__.py
deltatuner/scores/compute_de_score.py
deltatuner/scores/transformer_proxy.py
deltatuner/scores/transformer_proxy_ssf.py
deltatuner/scores/utils.py
deltatuner/search/BaseSearchEngine.py
deltatuner/search/EvolutionarySearchEngine.py
deltatuner/search/SearchEngineFactory.py
deltatuner/search/__init__.py
deltatuner/search/utils.py
deltatuner/tuner/__init__.py
deltatuner/tuner/deltatuner_lora.py
deltatuner/tuner/deltatuner_ssf.py
deltatuner/utils/__init__.py
deltatuner/utils/config.py
deltatuner/utils/save_and_load.py
e2eAIOK_deltatuner.egg-info/PKG-INFO
e2eAIOK_deltatuner.egg-info/SOURCES.txt
e2eAIOK_deltatuner.egg-info/dependency_links.txt
e2eAIOK_deltatuner.egg-info/requires.txt
e2eAIOK_deltatuner.egg-info/top_level.txt